<?xml version="1.0" encoding="utf-8"?>

<curveCfg>
	<unit name="A号站1">
		<group name="1-01柜1#进线">
			<line name="A_H1_01_Ia" color="008000" />
			<line name="A_H1_01_Ib" />
			<line name="A_H1_01_Ic" color="FF0000" />
		</group>
		<group name="1-03柜1#出线">
			<line name="A_H1_03_Ia" color="FF0000" />
			<line name="A_H1_03_Ib" />
			<line name="A_H1_03_Ic" color="008000" />
		</group>
	</unit>
	<unit name="2#A号站2">
		<group name="1-04柜2#出线">>
			<line name="A_H1_04_Ia" color="FF0000" />
			<line name="A_H1_04_Ib" />
			<line name="A_H1_04_Ic" color="008000" />
		</group>
	</unit>
</curveCfg>