<?xml version="1.0" encoding="GBK" ?>
<config>
    <dynamic name="配置文件列表">
        <configType type="1" name="站点配置文件" path="unitConfigs">
            <configFile name="中心电站.xml" md5="f639b46e98d87d6feb40b42fe1fea180" />
        </configType>
        <configType type="2" name="PIC配置文件" path="pictures">
            <configFile name="中心电站低压系统图.xml" md5="d91ef9965924e876bee96e8e37eebb79" />
            <configFile name="中心电站高压系统数据表.xml" md5="8fbc2098e758aec04fcb8f05bb7168d5" />
            <configFile name="中心电站高压系统图.xml" md5="2142442b3d8f9b4fdec1e7dc216fd659" />
        </configType>
        <configType type="4" name="NEMS基本配置文件" path="baseConfigs">
            <configFile name="CurveCfg.xml" md5="80cf96ed12a17ef470aec73e197785bf" />
        </configType>
    </dynamic>
</config>
